stepup/core/__init__.py
stepup/core/__main__.py
stepup/core/actions.py
stepup/core/api.py
stepup/core/asyncio.py
stepup/core/browse.py
stepup/core/call.py
stepup/core/cascade.py
stepup/core/clean.py
stepup/core/deferred_glob.py
stepup/core/director.py
stepup/core/enums.py
stepup/core/exceptions.py
stepup/core/file.py
stepup/core/hash.py
stepup/core/interact.py
stepup/core/job.py
stepup/core/logo.svg
stepup/core/nglob.py
stepup/core/pytest.py
stepup/core/render_jinja.py
stepup/core/reporter.py
stepup/core/rpc.py
stepup/core/runner.py
stepup/core/scheduler.py
stepup/core/script.py
stepup/core/startup.py
stepup/core/step.py
stepup/core/stepinfo.py
stepup/core/tui.py
stepup/core/utils.py
stepup/core/watcher.py
stepup/core/worker.py
stepup/core/workflow.py
stepup-3.2.0.dist-info/licenses/LICENSE
stepup-3.2.0.dist-info/METADATA
stepup-3.2.0.dist-info/WHEEL
stepup-3.2.0.dist-info/entry_points.txt
stepup-3.2.0.dist-info/top_level.txt
stepup-3.2.0.dist-info/RECORD
