Metadata-Version: 2.4
Name: stepup
Version: 3.2.0
Summary: StepUp Core provides the basic framework for the StepUp build tool
Author-email: Toon Verstraelen <toon.verstraelen@ugent.be>
License-Expression: GPL-3.0-or-later
Project-URL: Documentation, https://reproducible-reporting.github.io/stepup-core/
Project-URL: Issues, https://github.com/reproducible-reporting/stepup-core/issues
Project-URL: Source, https://github.com/reproducible-reporting/stepup-core/
Project-URL: Changelog, https://reproducible-reporting.github.io/stepup-core/changelog/
Classifier: Development Status :: 4 - Beta
Classifier: Environment :: Console
Classifier: Intended Audience :: Education
Classifier: Intended Audience :: Science/Research
Classifier: Natural Language :: English
Classifier: Operating System :: POSIX
Classifier: Operating System :: MacOS
Classifier: Programming Language :: Python :: 3
Classifier: Programming Language :: Python :: 3.11
Classifier: Programming Language :: Python :: 3.12
Classifier: Programming Language :: Python :: 3.13
Classifier: Programming Language :: Python :: 3.14
Classifier: Topic :: Software Development :: Build Tools
Requires-Python: >=3.11
License-File: LICENSE
Requires-Dist: asyncinotify>=4.0.9
Requires-Dist: attrs>=22.1.0
Requires-Dist: jinja2>=3.1.6
Requires-Dist: parse>=1.19.1
Requires-Dist: path>=16.14.0
Requires-Dist: pyyaml>=6.0
Requires-Dist: rich>=13.0.0
Provides-Extra: dev
Requires-Dist: psutil; extra == "dev"
Requires-Dist: pytest; extra == "dev"
Requires-Dist: pytest-asyncio>=0.24; extra == "dev"
Requires-Dist: pytest-xdist; extra == "dev"
Requires-Dist: mike; extra == "dev"
Requires-Dist: mkdocs; extra == "dev"
Requires-Dist: mkdocstrings[python]; extra == "dev"
Requires-Dist: mkdocs-macros-plugin; extra == "dev"
Requires-Dist: mkdocs-material; extra == "dev"
Requires-Dist: numpy; extra == "dev"
Requires-Dist: matplotlib; extra == "dev"
Dynamic: license-file
